{
  "tasks": [
    "masc",
    "mate",
    "mner",
    "mabsa",
    "mnre"
  ],
  "acc_matrix": [
    [
      76.66345226615236
    ],
    [
      15.525554484088715,
      88.14227349194906
    ],
    [
      0.0,
      81.41312184571017,
      92.79939482766773
    ],
    [
      56.219864995178405,
      81.88416246094688,
      88.90501631128552,
      83.90290795481855
    ],
    [
      6.653809064609451,
      0.7402066810862773,
      0.07186421445794525,
      0.3941360249939918,
      87.0
    ]
  ],
  "sessions": [
    {
      "session_name": "masc_1",
      "task_name": "masc",
      "start_time": "2025-04-11 05:34:26",
      "epochs": 20,
      "details": {
        "epoch_losses": [
          0.7942470600032926,
          0.5618654987189787,
          0.4410673584976238,
          0.3408744281565012,
          0.2376850945696623,
          0.12987039683780974,
          0.09096781846439178,
          0.08255868955356205,
          0.06390438913944646,
          0.06285508405197097,
          0.03535907999399962,
          0.03394645683079605,
          0.027851190451240394,
          0.023624243005295868,
          0.023584231335578933,
          0.021141864595701186,
          0.01259263601277963,
          0.017942057377553482,
          0.009510853874183994,
          0.009988053772274122
        ],
        "dev_metrics_history": [
          {
            "acc": 70.32085561497327,
            "micro_prec": 70.32085561497327,
            "micro_recall": 70.32085561497327,
            "micro_f1": 70.32085561497327,
            "label_counter": {
              "1": 670,
              "2": 303,
              "0": 149
            }
          },
          {
            "acc": 68.89483065953654,
            "micro_prec": 68.89483065953654,
            "micro_recall": 68.89483065953654,
            "micro_f1": 68.89483065953654,
            "label_counter": {
              "1": 670,
              "2": 303,
              "0": 149
            }
          },
          {
            "acc": 71.56862745098039,
            "micro_prec": 71.56862745098039,
            "micro_recall": 71.56862745098039,
            "micro_f1": 71.56862745098039,
            "label_counter": {
              "1": 670,
              "2": 303,
              "0": 149
            }
          },
          {
            "acc": 77.27272727272727,
            "micro_prec": 77.27272727272727,
            "micro_recall": 77.27272727272727,
            "micro_f1": 77.27272727272727,
            "label_counter": {
              "1": 670,
              "2": 303,
              "0": 149
            }
          },
          {
            "acc": 75.75757575757575,
            "micro_prec": 75.75757575757575,
            "micro_recall": 75.75757575757575,
            "micro_f1": 75.75757575757575,
            "label_counter": {
              "1": 670,
              "2": 303,
              "0": 149
            }
          },
          {
            "acc": 74.33155080213903,
            "micro_prec": 74.33155080213903,
            "micro_recall": 74.33155080213903,
            "micro_f1": 74.33155080213903,
            "label_counter": {
              "1": 670,
              "2": 303,
              "0": 149
            }
          },
          {
            "acc": 76.29233511586453,
            "micro_prec": 76.29233511586453,
            "micro_recall": 76.29233511586453,
            "micro_f1": 76.29233511586453,
            "label_counter": {
              "1": 670,
              "2": 303,
              "0": 149
            }
          },
          {
            "acc": 74.68805704099822,
            "micro_prec": 74.68805704099822,
            "micro_recall": 74.68805704099822,
            "micro_f1": 74.68805704099822,
            "label_counter": {
              "1": 670,
              "2": 303,
              "0": 149
            }
          },
          {
            "acc": 74.59893048128342,
            "micro_prec": 74.59893048128342,
            "micro_recall": 74.59893048128342,
            "micro_f1": 74.59893048128342,
            "label_counter": {
              "1": 670,
              "2": 303,
              "0": 149
            }
          },
          {
            "acc": 75.0445632798574,
            "micro_prec": 75.0445632798574,
            "micro_recall": 75.0445632798574,
            "micro_f1": 75.0445632798574,
            "label_counter": {
              "1": 670,
              "2": 303,
              "0": 149
            }
          },
          {
            "acc": 75.57932263814617,
            "micro_prec": 75.57932263814617,
            "micro_recall": 75.57932263814617,
            "micro_f1": 75.57932263814617,
            "label_counter": {
              "1": 670,
              "2": 303,
              "0": 149
            }
          },
          {
            "acc": 75.49019607843137,
            "micro_prec": 75.49019607843137,
            "micro_recall": 75.49019607843137,
            "micro_f1": 75.49019607843137,
            "label_counter": {
              "1": 670,
              "2": 303,
              "0": 149
            }
          },
          {
            "acc": 75.1336898395722,
            "micro_prec": 75.1336898395722,
            "micro_recall": 75.1336898395722,
            "micro_f1": 75.1336898395722,
            "label_counter": {
              "1": 670,
              "2": 303,
              "0": 149
            }
          },
          {
            "acc": 75.0445632798574,
            "micro_prec": 75.0445632798574,
            "micro_recall": 75.0445632798574,
            "micro_f1": 75.0445632798574,
            "label_counter": {
              "1": 670,
              "2": 303,
              "0": 149
            }
          },
          {
            "acc": 75.49019607843137,
            "micro_prec": 75.49019607843137,
            "micro_recall": 75.49019607843137,
            "micro_f1": 75.49019607843137,
            "label_counter": {
              "1": 670,
              "2": 303,
              "0": 149
            }
          },
          {
            "acc": 75.22281639928698,
            "micro_prec": 75.22281639928698,
            "micro_recall": 75.22281639928698,
            "micro_f1": 75.22281639928698,
            "label_counter": {
              "1": 670,
              "2": 303,
              "0": 149
            }
          },
          {
            "acc": 75.22281639928698,
            "micro_prec": 75.22281639928698,
            "micro_recall": 75.22281639928698,
            "micro_f1": 75.22281639928698,
            "label_counter": {
              "1": 670,
              "2": 303,
              "0": 149
            }
          },
          {
            "acc": 75.40106951871658,
            "micro_prec": 75.40106951871658,
            "micro_recall": 75.40106951871658,
            "micro_f1": 75.40106951871658,
            "label_counter": {
              "1": 670,
              "2": 303,
              "0": 149
            }
          },
          {
            "acc": 75.66844919786097,
            "micro_prec": 75.66844919786097,
            "micro_recall": 75.66844919786097,
            "micro_f1": 75.66844919786097,
            "label_counter": {
              "1": 670,
              "2": 303,
              "0": 149
            }
          },
          {
            "acc": 75.93582887700535,
            "micro_prec": 75.93582887700535,
            "micro_recall": 75.93582887700535,
            "micro_f1": 75.93582887700535,
            "label_counter": {
              "1": 670,
              "2": 303,
              "0": 149
            }
          }
        ],
        "final_dev_metrics": {
          "acc": 75.93582887700535,
          "micro_prec": 75.93582887700535,
          "micro_recall": 75.93582887700535,
          "micro_f1": 75.93582887700535,
          "label_counter": {
            "1": 670,
            "2": 303,
            "0": 149
          }
        },
        "final_test_metrics": {
          "acc": 76.66345226615236,
          "micro_prec": 76.66345226615236,
          "micro_recall": 76.66345226615236,
          "micro_f1": 76.66345226615236,
          "label_counter": {
            "1": 607,
            "2": 317,
            "0": 113
          }
        }
      },
      "final_metrics": {},
      "args": {
        "task_name": "masc",
        "session_name": "masc_1",
        "train_info_json": "checkpoints/train_info_twitter2015_none_text.json",
        "pretrained_model_path": "",
        "output_model_path": "/root/autodl-tmp/checkpoints/1.pt",
        "train_text_file": "data/MASC/twitter2015/train.txt",
        "test_text_file": "data/MASC/twitter2015/test.txt",
        "dev_text_file": "data/MASC/twitter2015/dev.txt",
        "image_dir": "data/img",
        "text_model_name": "microsoft/deberta-v3-base",
        "image_model_name": "google/vit-base-patch16-224-in21k",
        "fusion_strategy": "multi_head_attention",
        "num_heads": 8,
        "batch_size": 8,
        "lr": 1e-05,
        "epochs": 20,
        "num_labels": 3,
        "hidden_dim": 768,
        "step_size": 5,
        "gamma": 0.5,
        "mode": "text_only",
        "weight_decay": 1e-05,
        "dropout_prob": 0.1,
        "patience": 5,
        "ewc": 0,
        "ewc_dir": "ewc_params",
        "ewc_lambda": 100,
        "parallel": 0,
        "replay": 0,
        "memory_percentage": 0.05,
        "replay_frequency": 5,
        "memory_sampling_strategy": "random"
      },
      "fisher_file": "ewc_params/masc_1_fisher.pt"
    },
    {
      "session_name": "mate_1",
      "task_name": "mate",
      "start_time": "2025-04-11 05:53:04",
      "epochs": 20,
      "details": {
        "epoch_losses": [
          0.3526997812017424,
          0.2731231128862455,
          0.23258077941048685,
          0.2083588743198607,
          0.18994107212515632,
          0.17783225699323207,
          0.1633420217332978,
          0.16174097904401957,
          0.15686715171138882,
          0.15549108563880226,
          0.13996433951836676,
          0.13946756521876358,
          0.1336647206449404,
          0.1323379382620397,
          0.13935572056605214,
          0.1305407811770562,
          0.13423783110094026,
          0.13021299737065695,
          0.12799573198297814,
          0.12688972453245118
        ],
        "dev_metrics_history": [
          {
            "acc": 83.70794169731644,
            "micro_prec": 83.70794169731644,
            "micro_recall": 83.70794169731644,
            "micro_f1": 83.70794169731644,
            "label_counter": {
              "0": 19837,
              "1": 1122,
              "2": 1064
            }
          },
          {
            "acc": 88.5437951232802,
            "micro_prec": 88.5437951232802,
            "micro_recall": 88.5437951232802,
            "micro_f1": 88.5437951232802,
            "label_counter": {
              "0": 19837,
              "1": 1122,
              "2": 1064
            }
          },
          {
            "acc": 88.64823139445126,
            "micro_prec": 88.64823139445126,
            "micro_recall": 88.64823139445126,
            "micro_f1": 88.64823139445126,
            "label_counter": {
              "0": 19837,
              "1": 1122,
              "2": 1064
            }
          },
          {
            "acc": 88.4484402669936,
            "micro_prec": 88.4484402669936,
            "micro_recall": 88.4484402669936,
            "micro_f1": 88.4484402669936,
            "label_counter": {
              "0": 19837,
              "1": 1122,
              "2": 1064
            }
          },
          {
            "acc": 87.0998501566544,
            "micro_prec": 87.0998501566544,
            "micro_recall": 87.0998501566544,
            "micro_f1": 87.0998501566544,
            "label_counter": {
              "0": 19837,
              "1": 1122,
              "2": 1064
            }
          },
          {
            "acc": 88.23956772465151,
            "micro_prec": 88.23956772465151,
            "micro_recall": 88.23956772465151,
            "micro_f1": 88.23956772465151,
            "label_counter": {
              "0": 19837,
              "1": 1122,
              "2": 1064
            }
          },
          {
            "acc": 88.97970303773329,
            "micro_prec": 88.97970303773329,
            "micro_recall": 88.97970303773329,
            "micro_f1": 88.97970303773329,
            "label_counter": {
              "0": 19837,
              "1": 1122,
              "2": 1064
            }
          },
          {
            "acc": 89.27030831403533,
            "micro_prec": 89.27030831403533,
            "micro_recall": 89.27030831403533,
            "micro_f1": 89.27030831403533,
            "label_counter": {
              "0": 19837,
              "1": 1122,
              "2": 1064
            }
          },
          {
            "acc": 89.01602869727103,
            "micro_prec": 89.01602869727103,
            "micro_recall": 89.01602869727103,
            "micro_f1": 89.01602869727103,
            "label_counter": {
              "0": 19837,
              "1": 1122,
              "2": 1064
            }
          },
          {
            "acc": 87.35867048086092,
            "micro_prec": 87.35867048086092,
            "micro_recall": 87.35867048086092,
            "micro_f1": 87.35867048086092,
            "label_counter": {
              "0": 19837,
              "1": 1122,
              "2": 1064
            }
          },
          {
            "acc": 88.79353403260228,
            "micro_prec": 88.79353403260228,
            "micro_recall": 88.79353403260228,
            "micro_f1": 88.79353403260228,
            "label_counter": {
              "0": 19837,
              "1": 1122,
              "2": 1064
            }
          },
          {
            "acc": 89.12046496844208,
            "micro_prec": 89.12046496844208,
            "micro_recall": 89.12046496844208,
            "micro_f1": 89.12046496844208,
            "label_counter": {
              "0": 19837,
              "1": 1122,
              "2": 1064
            }
          },
          {
            "acc": 89.12046496844208,
            "micro_prec": 89.12046496844208,
            "micro_recall": 89.12046496844208,
            "micro_f1": 89.12046496844208,
            "label_counter": {
              "0": 19837,
              "1": 1122,
              "2": 1064
            }
          },
          {
            "acc": 89.01602869727103,
            "micro_prec": 89.01602869727103,
            "micro_recall": 89.01602869727103,
            "micro_f1": 89.01602869727103,
            "label_counter": {
              "0": 19837,
              "1": 1122,
              "2": 1064
            }
          },
          {
            "acc": 88.66639422422014,
            "micro_prec": 88.66639422422014,
            "micro_recall": 88.66639422422014,
            "micro_f1": 88.66639422422014,
            "label_counter": {
              "0": 19837,
              "1": 1122,
              "2": 1064
            }
          },
          {
            "acc": 88.85256322935113,
            "micro_prec": 88.85256322935113,
            "micro_recall": 88.85256322935113,
            "micro_f1": 88.85256322935113,
            "label_counter": {
              "0": 19837,
              "1": 1122,
              "2": 1064
            }
          },
          {
            "acc": 88.17599782046042,
            "micro_prec": 88.17599782046042,
            "micro_recall": 88.17599782046042,
            "micro_f1": 88.17599782046042,
            "label_counter": {
              "0": 19837,
              "1": 1122,
              "2": 1064
            }
          },
          {
            "acc": 88.30313762884258,
            "micro_prec": 88.30313762884258,
            "micro_recall": 88.30313762884258,
            "micro_f1": 88.30313762884258,
            "label_counter": {
              "0": 19837,
              "1": 1122,
              "2": 1064
            }
          },
          {
            "acc": 89.00694728238659,
            "micro_prec": 89.00694728238659,
            "micro_recall": 89.00694728238659,
            "micro_f1": 89.00694728238659,
            "label_counter": {
              "0": 19837,
              "1": 1122,
              "2": 1064
            }
          },
          {
            "acc": 88.64369068700904,
            "micro_prec": 88.64369068700904,
            "micro_recall": 88.64369068700904,
            "micro_f1": 88.64369068700904,
            "label_counter": {
              "0": 19837,
              "1": 1122,
              "2": 1064
            }
          }
        ],
        "final_dev_metrics": {
          "acc": 88.64369068700904,
          "micro_prec": 88.64369068700904,
          "micro_recall": 88.64369068700904,
          "micro_f1": 88.64369068700904,
          "label_counter": {
            "0": 19837,
            "1": 1122,
            "2": 1064
          }
        },
        "final_test_metrics": {
          "acc": 88.14227349194906,
          "micro_prec": 88.14227349194906,
          "micro_recall": 88.14227349194906,
          "micro_f1": 88.14227349194906,
          "label_counter": {
            "0": 18754,
            "1": 1037,
            "2": 1014
          }
        }
      },
      "final_metrics": {
        "AA": 51.833913988018885,
        "AIA": 64.24868312708563,
        "FM": 61.137897782063646,
        "BWT": -61.137897782063646
      },
      "args": {
        "task_name": "mate",
        "session_name": "mate_1",
        "train_info_json": "checkpoints/train_info_twitter2015_none_text.json",
        "pretrained_model_path": "/root/autodl-tmp/checkpoints/1.pt",
        "output_model_path": "/root/autodl-tmp/checkpoints/1.pt",
        "train_text_file": "data/MASC/twitter2015/train.txt",
        "test_text_file": "data/MASC/twitter2015/test.txt",
        "dev_text_file": "data/MASC/twitter2015/dev.txt",
        "image_dir": "data/img",
        "text_model_name": "microsoft/deberta-v3-base",
        "image_model_name": "google/vit-base-patch16-224-in21k",
        "fusion_strategy": "multi_head_attention",
        "num_heads": 8,
        "batch_size": 8,
        "lr": 5e-05,
        "epochs": 20,
        "num_labels": 3,
        "hidden_dim": 768,
        "step_size": 10,
        "gamma": 0.5,
        "mode": "text_only",
        "weight_decay": 1e-05,
        "dropout_prob": 0.1,
        "patience": 5,
        "ewc": 0,
        "ewc_dir": "ewc_params",
        "ewc_lambda": 100,
        "parallel": 0,
        "replay": 0,
        "memory_percentage": 0.05,
        "replay_frequency": 5,
        "memory_sampling_strategy": "random"
      },
      "fisher_file": "ewc_params/mate_1_fisher.pt"
    },
    {
      "session_name": "mner_1",
      "task_name": "mner",
      "start_time": "2025-04-11 06:12:14",
      "epochs": 20,
      "details": {
        "epoch_losses": [
          0.7233025308176969,
          0.46249174651388,
          0.3227662977493576,
          0.23574422488357838,
          0.19035589339418282,
          0.12528212564383148,
          0.10083224902911321,
          0.0724893937691574,
          0.05874989591192449,
          0.050550689167092926,
          0.038674006008097964,
          0.021965818353406004,
          0.016393743077096908,
          0.019247730202534827,
          0.02158125237697409,
          0.018356937995828774,
          0.026876976806464902,
          0.028501017391593587,
          0.01870408284561274,
          0.01257881456205074
        ],
        "dev_metrics_history": [
          {
            "acc": 74.70651838121718,
            "micro_prec": 74.70651838121718,
            "micro_recall": 74.70651838121718,
            "micro_f1": 74.70651838121718,
            "label_counter": {
              "0": 61550,
              "5": 543,
              "6": 399,
              "1": 567,
              "2": 629,
              "3": 250,
              "4": 232,
              "7": 233,
              "8": 337
            }
          },
          {
            "acc": 83.59901143033673,
            "micro_prec": 83.59901143033673,
            "micro_recall": 83.59901143033673,
            "micro_f1": 83.59901143033673,
            "label_counter": {
              "0": 61550,
              "5": 543,
              "6": 399,
              "1": 567,
              "2": 629,
              "3": 250,
              "4": 232,
              "7": 233,
              "8": 337
            }
          },
          {
            "acc": 85.05406240346,
            "micro_prec": 85.05406240346,
            "micro_recall": 85.05406240346,
            "micro_f1": 85.05406240346,
            "label_counter": {
              "0": 61550,
              "5": 543,
              "6": 399,
              "1": 567,
              "2": 629,
              "3": 250,
              "4": 232,
              "7": 233,
              "8": 337
            }
          },
          {
            "acc": 87.42199567500772,
            "micro_prec": 87.42199567500772,
            "micro_recall": 87.42199567500772,
            "micro_f1": 87.42199567500772,
            "label_counter": {
              "0": 61550,
              "5": 543,
              "6": 399,
              "1": 567,
              "2": 629,
              "3": 250,
              "4": 232,
              "7": 233,
              "8": 337
            }
          },
          {
            "acc": 87.37102255174545,
            "micro_prec": 87.37102255174545,
            "micro_recall": 87.37102255174545,
            "micro_f1": 87.37102255174545,
            "label_counter": {
              "0": 61550,
              "5": 543,
              "6": 399,
              "1": 567,
              "2": 629,
              "3": 250,
              "4": 232,
              "7": 233,
              "8": 337
            }
          },
          {
            "acc": 89.80846462774174,
            "micro_prec": 89.80846462774174,
            "micro_recall": 89.80846462774174,
            "micro_f1": 89.80846462774174,
            "label_counter": {
              "0": 61550,
              "5": 543,
              "6": 399,
              "1": 567,
              "2": 629,
              "3": 250,
              "4": 232,
              "7": 233,
              "8": 337
            }
          },
          {
            "acc": 89.87179487179488,
            "micro_prec": 89.87179487179488,
            "micro_recall": 89.87179487179488,
            "micro_f1": 89.87179487179488,
            "label_counter": {
              "0": 61550,
              "5": 543,
              "6": 399,
              "1": 567,
              "2": 629,
              "3": 250,
              "4": 232,
              "7": 233,
              "8": 337
            }
          },
          {
            "acc": 91.06116774791474,
            "micro_prec": 91.06116774791474,
            "micro_recall": 91.06116774791474,
            "micro_f1": 91.06116774791474,
            "label_counter": {
              "0": 61550,
              "5": 543,
              "6": 399,
              "1": 567,
              "2": 629,
              "3": 250,
              "4": 232,
              "7": 233,
              "8": 337
            }
          },
          {
            "acc": 91.16156935434044,
            "micro_prec": 91.16156935434044,
            "micro_recall": 91.16156935434044,
            "micro_f1": 91.16156935434044,
            "label_counter": {
              "0": 61550,
              "5": 543,
              "6": 399,
              "1": 567,
              "2": 629,
              "3": 250,
              "4": 232,
              "7": 233,
              "8": 337
            }
          },
          {
            "acc": 91.15230151374729,
            "micro_prec": 91.15230151374729,
            "micro_recall": 91.15230151374729,
            "micro_f1": 91.15230151374729,
            "label_counter": {
              "0": 61550,
              "5": 543,
              "6": 399,
              "1": 567,
              "2": 629,
              "3": 250,
              "4": 232,
              "7": 233,
              "8": 337
            }
          },
          {
            "acc": 91.83503243744208,
            "micro_prec": 91.83503243744208,
            "micro_recall": 91.83503243744208,
            "micro_f1": 91.83503243744208,
            "label_counter": {
              "0": 61550,
              "5": 543,
              "6": 399,
              "1": 567,
              "2": 629,
              "3": 250,
              "4": 232,
              "7": 233,
              "8": 337
            }
          },
          {
            "acc": 91.8628359592215,
            "micro_prec": 91.8628359592215,
            "micro_recall": 91.8628359592215,
            "micro_f1": 91.8628359592215,
            "label_counter": {
              "0": 61550,
              "5": 543,
              "6": 399,
              "1": 567,
              "2": 629,
              "3": 250,
              "4": 232,
              "7": 233,
              "8": 337
            }
          },
          {
            "acc": 91.84893419833179,
            "micro_prec": 91.84893419833179,
            "micro_recall": 91.84893419833179,
            "micro_f1": 91.84893419833179,
            "label_counter": {
              "0": 61550,
              "5": 543,
              "6": 399,
              "1": 567,
              "2": 629,
              "3": 250,
              "4": 232,
              "7": 233,
              "8": 337
            }
          },
          {
            "acc": 91.96787148594377,
            "micro_prec": 91.96787148594377,
            "micro_recall": 91.96787148594377,
            "micro_f1": 91.96787148594377,
            "label_counter": {
              "0": 61550,
              "5": 543,
              "6": 399,
              "1": 567,
              "2": 629,
              "3": 250,
              "4": 232,
              "7": 233,
              "8": 337
            }
          },
          {
            "acc": 92.0605498918752,
            "micro_prec": 92.0605498918752,
            "micro_recall": 92.0605498918752,
            "micro_f1": 92.0605498918752,
            "label_counter": {
              "0": 61550,
              "5": 543,
              "6": 399,
              "1": 567,
              "2": 629,
              "3": 250,
              "4": 232,
              "7": 233,
              "8": 337
            }
          },
          {
            "acc": 91.52610441767068,
            "micro_prec": 91.52610441767068,
            "micro_recall": 91.52610441767068,
            "micro_f1": 91.52610441767068,
            "label_counter": {
              "0": 61550,
              "5": 543,
              "6": 399,
              "1": 567,
              "2": 629,
              "3": 250,
              "4": 232,
              "7": 233,
              "8": 337
            }
          },
          {
            "acc": 91.7191844300278,
            "micro_prec": 91.7191844300278,
            "micro_recall": 91.7191844300278,
            "micro_f1": 91.7191844300278,
            "label_counter": {
              "0": 61550,
              "5": 543,
              "6": 399,
              "1": 567,
              "2": 629,
              "3": 250,
              "4": 232,
              "7": 233,
              "8": 337
            }
          },
          {
            "acc": 91.69138090824838,
            "micro_prec": 91.69138090824838,
            "micro_recall": 91.69138090824838,
            "micro_f1": 91.69138090824838,
            "label_counter": {
              "0": 61550,
              "5": 543,
              "6": 399,
              "1": 567,
              "2": 629,
              "3": 250,
              "4": 232,
              "7": 233,
              "8": 337
            }
          },
          {
            "acc": 91.94161260426321,
            "micro_prec": 91.94161260426321,
            "micro_recall": 91.94161260426321,
            "micro_f1": 91.94161260426321,
            "label_counter": {
              "0": 61550,
              "5": 543,
              "6": 399,
              "1": 567,
              "2": 629,
              "3": 250,
              "4": 232,
              "7": 233,
              "8": 337
            }
          },
          {
            "acc": 92.51158480074143,
            "micro_prec": 92.51158480074143,
            "micro_recall": 92.51158480074143,
            "micro_f1": 92.51158480074143,
            "label_counter": {
              "0": 61550,
              "5": 543,
              "6": 399,
              "1": 567,
              "2": 629,
              "3": 250,
              "4": 232,
              "7": 233,
              "8": 337
            }
          }
        ],
        "final_dev_metrics": {
          "acc": 92.51158480074143,
          "micro_prec": 92.51158480074143,
          "micro_recall": 92.51158480074143,
          "micro_f1": 92.51158480074143,
          "label_counter": {
            "0": 61550,
            "5": 543,
            "6": 399,
            "1": 567,
            "2": 629,
            "3": 250,
            "4": 232,
            "7": 233,
            "8": 337
          }
        },
        "final_test_metrics": {
          "acc": 92.79939482766773,
          "micro_prec": 92.79939482766773,
          "micro_recall": 92.79939482766773,
          "micro_f1": 92.79939482766773,
          "label_counter": {
            "0": 201119,
            "1": 1872,
            "2": 1995,
            "7": 750,
            "8": 1085,
            "5": 1720,
            "3": 859,
            "6": 1334,
            "4": 776
          }
        }
      },
      "final_metrics": {
        "AA": 58.07083889112596,
        "AIA": 62.18940171509907,
        "FM": 41.696301956195626,
        "BWT": -41.696301956195626
      },
      "args": {
        "task_name": "mner",
        "session_name": "mner_1",
        "train_info_json": "checkpoints/train_info_twitter2015_none_text.json",
        "pretrained_model_path": "/root/autodl-tmp/checkpoints/1.pt",
        "output_model_path": "/root/autodl-tmp/checkpoints/1.pt",
        "train_text_file": "data/MNER/twitter2015/train.txt",
        "test_text_file": "data/MNER/twitter2015/test.txt",
        "dev_text_file": "data/MNER/twitter2015/dev.txt",
        "image_dir": "data/img",
        "text_model_name": "microsoft/deberta-v3-base",
        "image_model_name": "google/vit-base-patch16-224-in21k",
        "fusion_strategy": "multi_head_attention",
        "num_heads": 8,
        "batch_size": 8,
        "lr": 5e-05,
        "epochs": 20,
        "num_labels": 9,
        "hidden_dim": 768,
        "step_size": 10,
        "gamma": 0.5,
        "mode": "text_only",
        "weight_decay": 1e-05,
        "dropout_prob": 0.1,
        "patience": 5,
        "ewc": 0,
        "ewc_dir": "ewc_params",
        "ewc_lambda": 100,
        "parallel": 0,
        "replay": 0,
        "memory_percentage": 0.05,
        "replay_frequency": 5,
        "memory_sampling_strategy": "random"
      },
      "fisher_file": "ewc_params/mner_1_fisher.pt"
    },
    {
      "session_name": "mabsa_1",
      "task_name": "mabsa",
      "start_time": "2025-04-11 06:49:11",
      "epochs": 20,
      "details": {
        "epoch_losses": [
          0.5486101608480042,
          0.3860555739989083,
          0.27582820238611055,
          0.1880871569363391,
          0.12202677776657943,
          0.06953149949827574,
          0.06425432515232332,
          0.03708578171980703,
          0.05030067525593442,
          0.04659458192330949,
          0.024195624727769826,
          0.010986967349247118,
          0.009514527346812489,
          0.01831674318492703,
          0.010962002909211115,
          0.010829679811567574,
          0.014922448782523481,
          0.012054146089633205,
          0.02267810703991168,
          0.01815270051905937
        ],
        "dev_metrics_history": [
          {
            "acc": 14.780002724424465,
            "micro_prec": 14.780002724424465,
            "micro_recall": 14.780002724424465,
            "micro_f1": 14.780002724424465,
            "label_counter": {
              "0": 19837,
              "1": 670,
              "5": 303,
              "6": 320,
              "2": 650,
              "3": 149,
              "4": 94
            }
          },
          {
            "acc": 55.378467965309,
            "micro_prec": 55.378467965309,
            "micro_recall": 55.378467965309,
            "micro_f1": 55.378467965309,
            "label_counter": {
              "0": 19837,
              "1": 670,
              "5": 303,
              "6": 320,
              "2": 650,
              "3": 149,
              "4": 94
            }
          },
          {
            "acc": 61.69913272487854,
            "micro_prec": 61.69913272487854,
            "micro_recall": 61.69913272487854,
            "micro_f1": 61.69913272487854,
            "label_counter": {
              "0": 19837,
              "1": 670,
              "5": 303,
              "6": 320,
              "2": 650,
              "3": 149,
              "4": 94
            }
          },
          {
            "acc": 56.431912091903925,
            "micro_prec": 56.431912091903925,
            "micro_recall": 56.431912091903925,
            "micro_f1": 56.431912091903925,
            "label_counter": {
              "0": 19837,
              "1": 670,
              "5": 303,
              "6": 320,
              "2": 650,
              "3": 149,
              "4": 94
            }
          },
          {
            "acc": 74.33138082913318,
            "micro_prec": 74.33138082913318,
            "micro_recall": 74.33138082913318,
            "micro_f1": 74.33138082913318,
            "label_counter": {
              "0": 19837,
              "1": 670,
              "5": 303,
              "6": 320,
              "2": 650,
              "3": 149,
              "4": 94
            }
          },
          {
            "acc": 79.72120056304772,
            "micro_prec": 79.72120056304772,
            "micro_recall": 79.72120056304772,
            "micro_f1": 79.72120056304772,
            "label_counter": {
              "0": 19837,
              "1": 670,
              "5": 303,
              "6": 320,
              "2": 650,
              "3": 149,
              "4": 94
            }
          },
          {
            "acc": 75.30309222176815,
            "micro_prec": 75.30309222176815,
            "micro_recall": 75.30309222176815,
            "micro_f1": 75.30309222176815,
            "label_counter": {
              "0": 19837,
              "1": 670,
              "5": 303,
              "6": 320,
              "2": 650,
              "3": 149,
              "4": 94
            }
          },
          {
            "acc": 80.70199337056714,
            "micro_prec": 80.70199337056714,
            "micro_recall": 80.70199337056714,
            "micro_f1": 80.70199337056714,
            "label_counter": {
              "0": 19837,
              "1": 670,
              "5": 303,
              "6": 320,
              "2": 650,
              "3": 149,
              "4": 94
            }
          },
          {
            "acc": 79.97548017981202,
            "micro_prec": 79.97548017981202,
            "micro_recall": 79.97548017981202,
            "micro_f1": 79.97548017981202,
            "label_counter": {
              "0": 19837,
              "1": 670,
              "5": 303,
              "6": 320,
              "2": 650,
              "3": 149,
              "4": 94
            }
          },
          {
            "acc": 81.64191981110656,
            "micro_prec": 81.64191981110656,
            "micro_recall": 81.64191981110656,
            "micro_f1": 81.64191981110656,
            "label_counter": {
              "0": 19837,
              "1": 670,
              "5": 303,
              "6": 320,
              "2": 650,
              "3": 149,
              "4": 94
            }
          },
          {
            "acc": 82.18226399673068,
            "micro_prec": 82.18226399673068,
            "micro_recall": 82.18226399673068,
            "micro_f1": 82.18226399673068,
            "label_counter": {
              "0": 19837,
              "1": 670,
              "5": 303,
              "6": 320,
              "2": 650,
              "3": 149,
              "4": 94
            }
          },
          {
            "acc": 84.09844253734732,
            "micro_prec": 84.09844253734732,
            "micro_recall": 84.09844253734732,
            "micro_f1": 84.09844253734732,
            "label_counter": {
              "0": 19837,
              "1": 670,
              "5": 303,
              "6": 320,
              "2": 650,
              "3": 149,
              "4": 94
            }
          },
          {
            "acc": 85.08831675975117,
            "micro_prec": 85.08831675975117,
            "micro_recall": 85.08831675975117,
            "micro_f1": 85.08831675975117,
            "label_counter": {
              "0": 19837,
              "1": 670,
              "5": 303,
              "6": 320,
              "2": 650,
              "3": 149,
              "4": 94
            }
          },
          {
            "acc": 84.41175135086047,
            "micro_prec": 84.41175135086047,
            "micro_recall": 84.41175135086047,
            "micro_f1": 84.41175135086047,
            "label_counter": {
              "0": 19837,
              "1": 670,
              "5": 303,
              "6": 320,
              "2": 650,
              "3": 149,
              "4": 94
            }
          },
          {
            "acc": 84.10752395223176,
            "micro_prec": 84.10752395223176,
            "micro_recall": 84.10752395223176,
            "micro_f1": 84.10752395223176,
            "label_counter": {
              "0": 19837,
              "1": 670,
              "5": 303,
              "6": 320,
              "2": 650,
              "3": 149,
              "4": 94
            }
          },
          {
            "acc": 84.4662398401671,
            "micro_prec": 84.4662398401671,
            "micro_recall": 84.4662398401671,
            "micro_f1": 84.4662398401671,
            "label_counter": {
              "0": 19837,
              "1": 670,
              "5": 303,
              "6": 320,
              "2": 650,
              "3": 149,
              "4": 94
            }
          },
          {
            "acc": 85.84661490260183,
            "micro_prec": 85.84661490260183,
            "micro_recall": 85.84661490260183,
            "micro_f1": 85.84661490260183,
            "label_counter": {
              "0": 19837,
              "1": 670,
              "5": 303,
              "6": 320,
              "2": 650,
              "3": 149,
              "4": 94
            }
          },
          {
            "acc": 85.57871316351088,
            "micro_prec": 85.57871316351088,
            "micro_recall": 85.57871316351088,
            "micro_f1": 85.57871316351088,
            "label_counter": {
              "0": 19837,
              "1": 670,
              "5": 303,
              "6": 320,
              "2": 650,
              "3": 149,
              "4": 94
            }
          },
          {
            "acc": 84.71143804204695,
            "micro_prec": 84.71143804204695,
            "micro_recall": 84.71143804204695,
            "micro_f1": 84.71143804204695,
            "label_counter": {
              "0": 19837,
              "1": 670,
              "5": 303,
              "6": 320,
              "2": 650,
              "3": 149,
              "4": 94
            }
          },
          {
            "acc": 83.51723198474322,
            "micro_prec": 83.51723198474322,
            "micro_recall": 83.51723198474322,
            "micro_f1": 83.51723198474322,
            "label_counter": {
              "0": 19837,
              "1": 670,
              "5": 303,
              "6": 320,
              "2": 650,
              "3": 149,
              "4": 94
            }
          }
        ],
        "final_dev_metrics": {
          "acc": 83.51723198474322,
          "micro_prec": 83.51723198474322,
          "micro_recall": 83.51723198474322,
          "micro_f1": 83.51723198474322,
          "label_counter": {
            "0": 19837,
            "1": 670,
            "5": 303,
            "6": 320,
            "2": 650,
            "3": 149,
            "4": 94
          }
        },
        "final_test_metrics": {
          "acc": 83.90290795481855,
          "micro_prec": 83.90290795481855,
          "micro_recall": 83.90290795481855,
          "micro_f1": 83.90290795481855,
          "label_counter": {
            "0": 18754,
            "1": 607,
            "5": 317,
            "2": 614,
            "6": 319,
            "3": 113,
            "4": 81
          }
        }
      },
      "final_metrics": {
        "AA": 77.72798793055733,
        "AIA": 66.07404826896364,
        "FM": 10.198692272786111,
        "BWT": -10.198692272786111
      },
      "args": {
        "task_name": "mabsa",
        "session_name": "mabsa_1",
        "train_info_json": "checkpoints/train_info_twitter2015_none_text.json",
        "pretrained_model_path": "/root/autodl-tmp/checkpoints/1.pt",
        "output_model_path": "/root/autodl-tmp/checkpoints/1.pt",
        "train_text_file": "data/MASC/twitter2015/train.txt",
        "test_text_file": "data/MASC/twitter2015/test.txt",
        "dev_text_file": "data/MASC/twitter2015/dev.txt",
        "image_dir": "data/img",
        "text_model_name": "microsoft/deberta-v3-base",
        "image_model_name": "google/vit-base-patch16-224-in21k",
        "fusion_strategy": "multi_head_attention",
        "num_heads": 8,
        "batch_size": 8,
        "lr": 5e-05,
        "epochs": 20,
        "num_labels": 7,
        "hidden_dim": 768,
        "step_size": 10,
        "gamma": 0.5,
        "mode": "text_only",
        "weight_decay": 1e-05,
        "dropout_prob": 0.1,
        "patience": 5,
        "ewc": 0,
        "ewc_dir": "ewc_params",
        "ewc_lambda": 100,
        "parallel": 0,
        "replay": 0,
        "memory_percentage": 0.05,
        "replay_frequency": 5,
        "memory_sampling_strategy": "random"
      },
      "fisher_file": "ewc_params/mabsa_1_fisher.pt"
    },
    {
      "session_name": "mnre_1",
      "task_name": "mnre",
      "start_time": "2025-04-11 07:09:28",
      "epochs": 20,
      "details": {
        "epoch_losses": [
          0.8768487573270837,
          0.5632257244790033,
          0.46655793958568886,
          0.36859816442630555,
          0.3193611113111406,
          0.2911789713999174,
          0.2521728525128809,
          0.21428467328575695,
          0.17445940867764875,
          0.15445704913197975,
          0.0990453990543756,
          0.07579240111936675,
          0.07725068706836723,
          0.06416818447448144,
          0.0670995255427589,
          0.06835815013272944,
          0.06715949245033463,
          0.06476361090565866,
          0.0636770070078426,
          0.05580115513923316
        ],
        "dev_metrics_history": [
          {
            "acc": 81.06995884773663,
            "micro_prec": 81.06995884773663,
            "micro_recall": 81.06995884773663,
            "micro_f1": 81.06995884773663,
            "label_counter": {
              "22": 166,
              "4": 2,
              "2": 45,
              "16": 1,
              "1": 25,
              "20": 4
            }
          },
          {
            "acc": 83.9506172839506,
            "micro_prec": 83.9506172839506,
            "micro_recall": 83.9506172839506,
            "micro_f1": 83.9506172839506,
            "label_counter": {
              "22": 166,
              "4": 2,
              "2": 45,
              "16": 1,
              "1": 25,
              "20": 4
            }
          },
          {
            "acc": 81.89300411522635,
            "micro_prec": 81.89300411522635,
            "micro_recall": 81.89300411522635,
            "micro_f1": 81.89300411522635,
            "label_counter": {
              "22": 166,
              "4": 2,
              "2": 45,
              "16": 1,
              "1": 25,
              "20": 4
            }
          },
          {
            "acc": 86.0082304526749,
            "micro_prec": 86.0082304526749,
            "micro_recall": 86.0082304526749,
            "micro_f1": 86.0082304526749,
            "label_counter": {
              "22": 166,
              "4": 2,
              "2": 45,
              "16": 1,
              "1": 25,
              "20": 4
            }
          },
          {
            "acc": 84.36213991769547,
            "micro_prec": 84.36213991769547,
            "micro_recall": 84.36213991769547,
            "micro_f1": 84.36213991769547,
            "label_counter": {
              "22": 166,
              "4": 2,
              "2": 45,
              "16": 1,
              "1": 25,
              "20": 4
            }
          },
          {
            "acc": 87.24279835390946,
            "micro_prec": 87.24279835390946,
            "micro_recall": 87.24279835390946,
            "micro_f1": 87.24279835390946,
            "label_counter": {
              "22": 166,
              "4": 2,
              "2": 45,
              "16": 1,
              "1": 25,
              "20": 4
            }
          },
          {
            "acc": 83.53909465020575,
            "micro_prec": 83.53909465020575,
            "micro_recall": 83.53909465020575,
            "micro_f1": 83.53909465020575,
            "label_counter": {
              "22": 166,
              "4": 2,
              "2": 45,
              "16": 1,
              "1": 25,
              "20": 4
            }
          },
          {
            "acc": 86.0082304526749,
            "micro_prec": 86.0082304526749,
            "micro_recall": 86.0082304526749,
            "micro_f1": 86.0082304526749,
            "label_counter": {
              "22": 166,
              "4": 2,
              "2": 45,
              "16": 1,
              "1": 25,
              "20": 4
            }
          },
          {
            "acc": 84.36213991769547,
            "micro_prec": 84.36213991769547,
            "micro_recall": 84.36213991769547,
            "micro_f1": 84.36213991769547,
            "label_counter": {
              "22": 166,
              "4": 2,
              "2": 45,
              "16": 1,
              "1": 25,
              "20": 4
            }
          },
          {
            "acc": 88.88888888888889,
            "micro_prec": 88.88888888888889,
            "micro_recall": 88.88888888888889,
            "micro_f1": 88.88888888888889,
            "label_counter": {
              "22": 166,
              "4": 2,
              "2": 45,
              "16": 1,
              "1": 25,
              "20": 4
            }
          },
          {
            "acc": 87.24279835390946,
            "micro_prec": 87.24279835390946,
            "micro_recall": 87.24279835390946,
            "micro_f1": 87.24279835390946,
            "label_counter": {
              "22": 166,
              "4": 2,
              "2": 45,
              "16": 1,
              "1": 25,
              "20": 4
            }
          },
          {
            "acc": 88.06584362139918,
            "micro_prec": 88.06584362139918,
            "micro_recall": 88.06584362139918,
            "micro_f1": 88.06584362139918,
            "label_counter": {
              "22": 166,
              "4": 2,
              "2": 45,
              "16": 1,
              "1": 25,
              "20": 4
            }
          },
          {
            "acc": 88.06584362139918,
            "micro_prec": 88.06584362139918,
            "micro_recall": 88.06584362139918,
            "micro_f1": 88.06584362139918,
            "label_counter": {
              "22": 166,
              "4": 2,
              "2": 45,
              "16": 1,
              "1": 25,
              "20": 4
            }
          },
          {
            "acc": 86.83127572016461,
            "micro_prec": 86.83127572016461,
            "micro_recall": 86.83127572016461,
            "micro_f1": 86.83127572016461,
            "label_counter": {
              "22": 166,
              "4": 2,
              "2": 45,
              "16": 1,
              "1": 25,
              "20": 4
            }
          },
          {
            "acc": 89.30041152263375,
            "micro_prec": 89.30041152263375,
            "micro_recall": 89.30041152263375,
            "micro_f1": 89.30041152263375,
            "label_counter": {
              "22": 166,
              "4": 2,
              "2": 45,
              "16": 1,
              "1": 25,
              "20": 4
            }
          },
          {
            "acc": 89.30041152263375,
            "micro_prec": 89.30041152263375,
            "micro_recall": 89.30041152263375,
            "micro_f1": 89.30041152263375,
            "label_counter": {
              "22": 166,
              "4": 2,
              "2": 45,
              "16": 1,
              "1": 25,
              "20": 4
            }
          },
          {
            "acc": 88.47736625514403,
            "micro_prec": 88.47736625514403,
            "micro_recall": 88.47736625514403,
            "micro_f1": 88.47736625514403,
            "label_counter": {
              "22": 166,
              "4": 2,
              "2": 45,
              "16": 1,
              "1": 25,
              "20": 4
            }
          },
          {
            "acc": 86.83127572016461,
            "micro_prec": 86.83127572016461,
            "micro_recall": 86.83127572016461,
            "micro_f1": 86.83127572016461,
            "label_counter": {
              "22": 166,
              "4": 2,
              "2": 45,
              "16": 1,
              "1": 25,
              "20": 4
            }
          },
          {
            "acc": 86.83127572016461,
            "micro_prec": 86.83127572016461,
            "micro_recall": 86.83127572016461,
            "micro_f1": 86.83127572016461,
            "label_counter": {
              "22": 166,
              "4": 2,
              "2": 45,
              "16": 1,
              "1": 25,
              "20": 4
            }
          },
          {
            "acc": 86.83127572016461,
            "micro_prec": 86.83127572016461,
            "micro_recall": 86.83127572016461,
            "micro_f1": 86.83127572016461,
            "label_counter": {
              "22": 166,
              "4": 2,
              "2": 45,
              "16": 1,
              "1": 25,
              "20": 4
            }
          }
        ],
        "final_dev_metrics": {
          "acc": 86.83127572016461,
          "micro_prec": 86.83127572016461,
          "micro_recall": 86.83127572016461,
          "micro_f1": 86.83127572016461,
          "label_counter": {
            "22": 166,
            "4": 2,
            "2": 45,
            "16": 1,
            "1": 25,
            "20": 4
          }
        },
        "final_test_metrics": {
          "acc": 87.0,
          "micro_prec": 87.0,
          "micro_recall": 87.0,
          "micro_f1": 87.0,
          "label_counter": {
            "2": 74,
            "22": 191,
            "1": 29,
            "4": 3,
            "16": 3
          }
        }
      },
      "final_metrics": {
        "AA": 18.972003197029533,
        "AIA": 56.65363925457682,
        "FM": 83.41200313886,
        "BWT": -83.41200313886
      },
      "args": {
        "task_name": "mnre",
        "session_name": "mnre_1",
        "train_info_json": "checkpoints/train_info_twitter2015_none_text.json",
        "pretrained_model_path": "/root/autodl-tmp/checkpoints/1.pt",
        "output_model_path": "/root/autodl-tmp/checkpoints/1.pt",
        "train_text_file": "data/MNRE/twitter2015/train.txt",
        "test_text_file": "data/MNRE/twitter2015/test.txt",
        "dev_text_file": "data/MNRE/twitter2015/dev.txt",
        "image_dir": "data/img",
        "text_model_name": "microsoft/deberta-v3-base",
        "image_model_name": "google/vit-base-patch16-224-in21k",
        "fusion_strategy": "multi_head_attention",
        "num_heads": 8,
        "batch_size": 8,
        "lr": 5e-05,
        "epochs": 20,
        "num_labels": 23,
        "hidden_dim": 768,
        "step_size": 10,
        "gamma": 0.5,
        "mode": "text_only",
        "weight_decay": 1e-05,
        "dropout_prob": 0.1,
        "patience": 5,
        "ewc": 0,
        "ewc_dir": "ewc_params",
        "ewc_lambda": 100,
        "parallel": 0,
        "replay": 0,
        "memory_percentage": 0.05,
        "replay_frequency": 5,
        "memory_sampling_strategy": "random"
      },
      "fisher_file": "ewc_params/mnre_1_fisher.pt"
    }
  ]
}